cyborgclient/__init__.py
cyborgclient/exceptions.py
cyborgclient/i18n.py
cyborgclient/shell.py
cyborgclient/version.py
cyborgclient/common/__init__.py
cyborgclient/common/base.py
cyborgclient/common/cliutils.py
cyborgclient/common/http.py
cyborgclient/common/httpclient.py
cyborgclient/common/utils.py
cyborgclient/common/apiclient/__init__.py
cyborgclient/common/apiclient/base.py
cyborgclient/common/apiclient/exceptions.py
cyborgclient/osc/__init__.py
cyborgclient/osc/plugin.py
cyborgclient/osc/v1/__init__.py
cyborgclient/osc/v1/accelerator.py
cyborgclient/osc/v2/__init__.py
cyborgclient/osc/v2/accelerator_request.py
cyborgclient/osc/v2/attribute.py
cyborgclient/osc/v2/deployable.py
cyborgclient/osc/v2/device.py
cyborgclient/osc/v2/device_profile.py
cyborgclient/tests/__init__.py
cyborgclient/tests/base.py
cyborgclient/tests/test_cyborgclient.py
cyborgclient/tests/functional/__init__.py
cyborgclient/tests/unit/__init__.py
cyborgclient/tests/unit/base.py
cyborgclient/tests/unit/test_shell.py
cyborgclient/tests/unit/utils.py
cyborgclient/tests/unit/common/__init__.py
cyborgclient/tests/unit/common/test_httpclient.py
cyborgclient/tests/unit/common/test_utils.py
cyborgclient/tests/unit/osc/__init__.py
cyborgclient/tests/unit/osc/fakes.py
cyborgclient/tests/unit/osc/test_plugin.py
cyborgclient/tests/unit/osc/v2/__init__.py
cyborgclient/tests/unit/osc/v2/fakes.py
cyborgclient/tests/unit/osc/v2/test_accelerator_request.py
cyborgclient/tests/unit/osc/v2/test_attribute.py
cyborgclient/tests/unit/osc/v2/test_deployable.py
cyborgclient/tests/unit/osc/v2/test_device.py
cyborgclient/tests/unit/osc/v2/test_device_profile.py
cyborgclient/tests/unit/v1/__init__.py
cyborgclient/tests/unit/v1/shell_test_base.py
cyborgclient/tests/unit/v1/test_accelerators.py
cyborgclient/tests/unit/v1/test_accelerators_shell.py
cyborgclient/tests/unit/v1/test_client.py
cyborgclient/tests/unit/v1/test_deployables.py
cyborgclient/v1/__init__.py
cyborgclient/v1/accelerators.py
python_cyborgclient-2.6.0.dist-info/AUTHORS
python_cyborgclient-2.6.0.dist-info/LICENSE
python_cyborgclient-2.6.0.dist-info/METADATA
python_cyborgclient-2.6.0.dist-info/WHEEL
python_cyborgclient-2.6.0.dist-info/entry_points.txt
python_cyborgclient-2.6.0.dist-info/pbr.json
python_cyborgclient-2.6.0.dist-info/top_level.txt
python_cyborgclient-2.6.0.dist-info/RECORD
