Metadata-Version: 2.1
Name: python-cyborgclient
Version: 2.6.0
Summary: Python client for cyborg API
Home-page: https://docs.openstack.org/python-cyborgclient/latest/
Author: OpenStack
Author-email: openstack-discuss@lists.openstack.org
Classifier: Environment :: OpenStack
Classifier: Intended Audience :: Information Technology
Classifier: Intended Audience :: System Administrators
Classifier: License :: OSI Approved :: Apache Software License
Classifier: Operating System :: POSIX :: Linux
Classifier: Programming Language :: Python
Classifier: Programming Language :: Python :: Implementation :: CPython
Classifier: Programming Language :: Python :: 3 :: Only
Classifier: Programming Language :: Python :: 3
Classifier: Programming Language :: Python :: 3.8
Classifier: Programming Language :: Python :: 3.9
Classifier: Programming Language :: Python :: 3.10
Classifier: Programming Language :: Python :: 3.11
Requires-Python: >=3.8
License-File: LICENSE
License-File: AUTHORS
Requires-Dist: pbr !=2.1.0,>=2.0.0
Requires-Dist: keystoneauth1 >=3.3.0
Requires-Dist: stevedore >=1.20.0
Requires-Dist: requests >=2.14.2
Requires-Dist: oslo.i18n >=3.15.3
Requires-Dist: oslo.log >=5.0.0
Requires-Dist: oslo.serialization !=2.19.1,>=2.18.0
Requires-Dist: oslo.utils >=3.33.0
Requires-Dist: os-client-config >=1.28.0
Requires-Dist: osc-lib >=1.14.0
Requires-Dist: PrettyTable >=0.7.1
Requires-Dist: cryptography >=2.7
Requires-Dist: decorator >=3.4.0
Requires-Dist: openstacksdk >=0.46.0
